LICENSE
README.md
setup.cfg
setup.py
transaction_analyze/colors.py
transaction_analyze/exporter.py
transaction_analyze/getQuark.py
transaction_analyze/getTransactions.py
transaction_analyze/prepareGraph.py
transaction_analyze/r_address_list1.py
transaction_analyze/r_address_list2.py
transaction_analyze/r_address_list3.py
transaction_analyze/requester.py
transaction_analyze/resource.py
transaction_analyze/utils.py
transaction_analyze.egg-info/PKG-INFO
transaction_analyze.egg-info/SOURCES.txt
transaction_analyze.egg-info/dependency_links.txt
transaction_analyze.egg-info/requires.txt
transaction_analyze.egg-info/top_level.txt