Metadata-Version: 2.1
Name: transaction-analyze
Version: 1.0.3
Summary: Transaction Analyze.
Home-page: UNKNOWN
Author: Jordan
License: Python Script
Platform: UNKNOWN
Provides-Extra: dev
License-File: LICENSE
